{"version":1,"date":"2022-10-13","title":"Oops... I Failed","measurement":"yds","body":[{"Warm Up":[{"repetitions":"3","distance":100,"stroke":"Free","description":"Moderate.","cycle":null},{"repetitions":"8","distance":"50","stroke":"IM","description":"Carry-over.","cycle":null}]},{"Main Set":[{"repetitions":1,"distance":"50","stroke":"Free","description":"Sprint for time.","cycle":null},{"repetitions":"8","distance":100,"stroke":"Free","description":"@2:00. Sprint from start.","cycle":null},{"repetitions":"3","distance":"50","stroke":"Free","description":"Sprint for time. Beat previous time.","cycle":null},{"repetitions":1,"distance":100,"stroke":"Choice","description":"Free. Fly if failed to beat time on any of previous 50's.","cycle":null}]},{"Kick":[{"repetitions":"8","distance":"25","stroke":"Free","description":"Underwaters.","cycle":null}]},{"Warm Down":[{"repetitions":1,"distance":"200","stroke":"Free","description":"Easy.","cycle":null}]}],"tags":["sprint","short"]}