{"version":1,"date":"2024-02-27","title":"Hold Please","measurement":"yds","body":[{"Warm Up":[{"repetitions":"3","distance":100,"stroke":"Free","description":"Moderate.","cycle":null},{"repetitions":"8","distance":"50","stroke":"IM","description":"Carry-over.","cycle":null}]},{"Main Set":[{"repetitions":"1","distance":"400","stroke":"Free","description":"Pull.","cycle":null},{"repetitions":"4","distance":"75","stroke":"Free","description":"Descend.","cycle":null},{"repetitions":1,"distance":"200","stroke":"Free","description":"Pull.","cycle":null},{"repetitions":"4","distance":"75","stroke":"Free","description":"Fast in the flags.","cycle":null},{"repetitions":1,"distance":100,"stroke":"Free","description":"Pull.","cycle":null},{"repetitions":"4","distance":"75","stroke":"Free","description":"Distance per stroke.","cycle":null}]},{"Warm Down":[{"repetitions":1,"distance":"200","stroke":"Free","description":"Easy.","cycle":null}]}],"tags":["freestyle","pull","distance"]}